LICENSE
MANIFEST.in
README.md
pyproject.toml
setup.py
bin/.gitkeep
plum_tools/.plum_tools.yaml
plum_tools/__init__.py
plum_tools/conf.py
plum_tools/exceptions.py
plum_tools/find_imports.py
plum_tools/gitrepo.py
plum_tools/gitstash.py
plum_tools/pipmi.py
plum_tools/pping.py
plum_tools/prn.py
plum_tools/pssh.py
plum_tools.egg-info/PKG-INFO
plum_tools.egg-info/SOURCES.txt
plum_tools.egg-info/dependency_links.txt
plum_tools.egg-info/entry_points.txt
plum_tools.egg-info/requires.txt
plum_tools.egg-info/top_level.txt
plum_tools/utils/__init__.py
plum_tools/utils/git.py
plum_tools/utils/parser.py
plum_tools/utils/printer.py
plum_tools/utils/sshconf.py
plum_tools/utils/utils.py
tests/test_conf.py
tests/test_gitrepo.py
tests/test_gitstash.py
tests/test_main.py
tests/test_pipmi.py
tests/test_pping.py
tests/test_prn.py
tests/test_pssh.py