Metadata-Version: 2.4
Name: plum_tools
Version: 0.4.0
Summary: linux下常用的工具包
Author-email: seekplum <1131909224m@sina.cn>
Project-URL: Homepage, https://github.com/seekplum/plum_tools
Project-URL: Documentation, https://github.com/seekplum/plum_tools
Project-URL: Repository, https://github.com/seekplum/plum_tools.git
Project-URL: Bug Tracker, https://github.com/seekplum/plum_tools/issues
Project-URL: Changelog, https://github.com/seekplum/plum_tools/blob/master/CHANGELOG.md
Classifier: Programming Language :: Python
Classifier: Programming Language :: Python :: 3
Classifier: Programming Language :: Python :: 3.8
Classifier: Programming Language :: Python :: 3.9
Classifier: Programming Language :: Python :: 3.10
Classifier: Programming Language :: Python :: 3.11
Classifier: Programming Language :: Python :: 3.12
Requires-Python: >=3.8
License-File: LICENSE
Requires-Dist: pyyaml
Requires-Dist: paramiko
Dynamic: license-file
